gpulr/__init__.py
gpulr/action.py
gpulr/class_perso.py
gpulr/datas.py
gpulr/fonctions.py
gpulr/setup.py
gpulr-1.10.dist-info/METADATA
gpulr-1.10.dist-info/WHEEL
gpulr-1.10.dist-info/entry_points.txt
gpulr-1.10.dist-info/top_level.txt
gpulr-1.10.dist-info/RECORD
