Metadata-Version: 2.1
Name: gpulr
Version: 1.10
Summary: Module pour gérer les connexions et récupérer des informations depuis le site GPU
Home-page: https://github.com/Paulin17/GPU_Python_Module
Author: DOYON Paulin
Author-email: contact@paulinodoyn.fr
Classifier: Programming Language :: Python :: 3
Classifier: License :: OSI Approved :: MIT License
Classifier: Operating System :: OS Independent
Requires-Python: >=3.6
Requires-Dist: requests
Requires-Dist: beautifulsoup4
